kcpy/__init__.py
kcpy/checkpoint.py
kcpy/core.py
t/__init__.py
t/unit/__init__.py
t/unit/test_core.py
kcpy-0.1.7.dist-info/LICENSE
kcpy-0.1.7.dist-info/METADATA
kcpy-0.1.7.dist-info/WHEEL
kcpy-0.1.7.dist-info/top_level.txt
kcpy-0.1.7.dist-info/RECORD
