Metadata-Version: 2.1
Name: kcpy
Version: 0.1.7
Summary: A kinesis consumer is purely written in python.
Home-page: UNKNOWN
Author: Hengfeng Li
Author-email: hengf.li@gmail.com
License: MIT License
Keywords: kinesis,consumer,stream,processing,queue
Platform: UNKNOWN
Classifier: Development Status :: 3 - Alpha
Classifier: License :: OSI Approved :: MIT License
Classifier: Programming Language :: Python :: 3 :: Only
Classifier: Programming Language :: Python :: 3.6
Classifier: Programming Language :: Python :: 3.7
Classifier: Programming Language :: Python :: Implementation :: CPython
Classifier: Operating System :: POSIX
Classifier: Operating System :: Microsoft :: Windows
Classifier: Operating System :: MacOS :: MacOS X
Classifier: Operating System :: Unix
Classifier: Environment :: No Input/Output (Daemon)
Classifier: Intended Audience :: Developers
Requires-Python: >=3.6.0
Requires-Dist: boto3
